[
    {"slug": "html", "title": "Learn HTML"},
    {"slug": "css", "title": "Learn CSS"},
    {"slug": "css-selectors", "title": "Master the CSS Selectors"},
    {"slug": "layouts", "title": "Display vs Position"},
    {"slug": "forms", "title": "Create FORMS"},
    {"slug": "bootstrap", "title": "Bootstrap 4"},
    {"slug": "js-beginner", "title": "General Javascript"},
    {"slug": "the-dom", "title": "Work with the DOM"},
    {"slug": "jquery-dom", "title": "Work with the DOM using jQuery"},
    {"slug": "events", "title": "Javascript Events"},
    {"slug": "object-oriented-programing-php", "title": "Object Oriented in PHP"},
    {"slug": "jquery-ajax", "title": "Ajax with jQuery"},
    {"slug": "functions", "title": "Functions with Javascript"},
    {"slug": "js-ajax", "title": "Ajax with XMLHTTPRequest"},
    {"slug": "react-js", "title": "Rendering with React.js"},
    {"slug": "sql", "title": "sql", "base": "https://sqlbolt.com/lesson/select_queries_introduction"},
    {"slug": "git", "title": "git", "base": "https://try.github.io/levels/1/challenges/1"},
    {"slug": "the-command-line", "title": "The Command Line (terminal)", "base": "https://cmdchallenge.com/"},
    {"slug": "javascript-modules", "title": "Javascript Modules (import vs export)"},
    {"slug": "from-js-to-php", "title": "Going from JS to PHP"}
]